good_utilities/config_utils.py
good_utilities/data_utils.py
good_utilities/date_utils.py
good_utilities/file_utils.py
good_utilities/logo.png
good_utilities/math_utils.py
good_utilities/name_utils.py
good_utilities/network_utils.py
good_utilities/os_utils.py
good_utilities/string_utils.py
good_utilities/text_utils.py
good_utilities-0.1.58.dist-info/METADATA
good_utilities-0.1.58.dist-info/WHEEL
good_utilities-0.1.58.dist-info/RECORD
